fifostr/__init__.py
fifostr/fifostr.py
FIFOStr-1.1.20.dist-info/LICENSE.txt
FIFOStr-1.1.20.dist-info/METADATA
FIFOStr-1.1.20.dist-info/WHEEL
FIFOStr-1.1.20.dist-info/top_level.txt
FIFOStr-1.1.20.dist-info/RECORD
