Metadata-Version: 2.1
Name: FIFOStr
Version: 1.1.20
Summary: fifostr - A FIFO (first in first out) buffer for strings derived from deque with pattern match callbacks
Home-page: https://github.com/deftio/fifostr
Author: manu chatterjee
Author-email: deftio@deftio.com
License: BSD License
Download-URL: https://pypi.python.org/pypi/fifostr
Keywords: string stream parsing,parser utilities
Platform: UNKNOWN
Classifier: Development Status :: 5 - Production/Stable
Classifier: Intended Audience :: Developers
Classifier: License :: OSI Approved :: BSD License
Classifier: Programming Language :: Python :: 2
Classifier: Programming Language :: Python :: 2.7
Classifier: Programming Language :: Python :: 3
Classifier: Programming Language :: Python :: 3.3
Classifier: Programming Language :: Python :: 3.4
Classifier: Programming Language :: Python :: 3.5
Classifier: Programming Language :: Python :: 3.6
Classifier: Programming Language :: Python :: 3.7
Classifier: Programming Language :: Python :: 3.8
Classifier: Programming Language :: Python :: 3.9
Provides-Extra: dev
Requires-Dist: check-manifest; extra == 'dev'
Provides-Extra: test
Requires-Dist: pytest; extra == 'test'
